setup.cfg
setup.py
bcresolver/__init__.py
bcresolver/namecoin.py
bcresolver.egg-info/PKG-INFO
bcresolver.egg-info/SOURCES.txt
bcresolver.egg-info/dependency_links.txt
bcresolver.egg-info/requires.txt
bcresolver.egg-info/top_level.txt