Metadata-Version: 1.1
Name: bcresolver
Version: 0.0.2
Summary: Blockchain to DNS with DNSSEC Resolver Library
Home-page: https://github.com/netkicorp/blockchain-resolver
Author: mdavid
Author-email: opensource@netki.com
License: BSD
Download-URL: https://github.com/netkicorp/blockchain-resolver/tarball/0.0.2
Platform: any
